testbed/__init__.py
testbed/actuator.py
testbed/camera.py
testbed/pixboard.py
testbed/sensor.py
pop_testbed-0.2.1.dist-info/METADATA
pop_testbed-0.2.1.dist-info/WHEEL
pop_testbed-0.2.1.dist-info/top_level.txt
pop_testbed-0.2.1.dist-info/RECORD
