Metadata-Version: 2.4
Name: pop-testbed
Version: 0.2.1
Summary: Pop plus for Testbed II
Home-page: https://github.com/hanback-lab/testbedii
Author: HBE Lab
Author-email: lab@hanback.co.kr
Classifier: Programming Language :: Python :: 3
Classifier: Operating System :: OS Independent
Requires-Python: >=3.10
Requires-Dist: paho-mqtt
Dynamic: author
Dynamic: author-email
Dynamic: classifier
Dynamic: home-page
Dynamic: requires-dist
Dynamic: requires-python
Dynamic: summary
